README
setup.py
watermarker/__init__.py
watermarker/sorl_engine.py
watermarker.egg-info/PKG-INFO
watermarker.egg-info/SOURCES.txt
watermarker.egg-info/dependency_links.txt
watermarker.egg-info/requires.txt
watermarker.egg-info/top_level.txt