Metadata-Version: 1.0
Name: watermarker
Version: 1.0
Summary: Library for add text watermarks to images using PIL, support sorl-thumbnail integration
Home-page: http://bitbucket.org/zeus/watermarker
Author: Pavel Zhukov
Author-email: gelios@gmail.com
License: GPL
Keywords: watermark,library
Platform: UNKNOWN
